qr_payment_cz/__init__.py
qr_payment_cz/app.py
qr_payment_cz/conftest.py
qr_payment_cz/main.py
qr_payment_cz/qr-payment-cz-server.service
qr_payment_cz/server.py
qr_payment_cz/libs/__init__.py
qr_payment_cz/libs/exceptions.py
qr_payment_cz/libs/iban_calc.py
qr_payment_cz/libs/print.py
qr_payment_cz/libs/str_generator.py
qr_payment_cz/resources/static/placeholder.txt
qr_payment_cz/resources/static/qr-icon.png
qr_payment_cz/resources/templates/index.html
qr_payment_cz/tests/__init__.py
qr_payment_cz/tests/test_iban_calc.py
qr_payment_cz/tests/test_str_generator.py
qr_payment_cz/web_app/__init__.py
qr_payment_cz/web_app/web_server_app.py
qr_payment_cz-0.2.17.dist-info/METADATA
qr_payment_cz-0.2.17.dist-info/WHEEL
qr_payment_cz-0.2.17.dist-info/entry_points.txt
qr_payment_cz-0.2.17.dist-info/top_level.txt
qr_payment_cz-0.2.17.dist-info/RECORD
