Metadata-Version: 2.4
Name: qr-payment-cz
Version: 0.2.17
Summary: QR code or string generator for CZ banks payments
Author-email: Ales Adamek <alda78@seznam.cz>
License-Expression: GPL-3.0-or-later
Project-URL: Homepage, https://gitlab.com/alda78/qr-payment-cz
Requires-Python: >=3.8
Requires-Dist: al78tools
Requires-Dist: flask
Requires-Dist: pytest
Requires-Dist: qrcode[pil]
Requires-Dist: refdatatypes
Provides-Extra: dev
Requires-Dist: ruff; extra == "dev"
